lib/__init__.py
lib/cli.py
lib/framework.py
PySimpleObfuscate-0.6.dist-info/METADATA
PySimpleObfuscate-0.6.dist-info/WHEEL
PySimpleObfuscate-0.6.dist-info/entry_points.txt
PySimpleObfuscate-0.6.dist-info/top_level.txt
PySimpleObfuscate-0.6.dist-info/RECORD
