Metadata-Version: 2.1
Name: PySimpleObfuscate
Version: 0.6
Summary: A Simple Python Obfuscator
